{"fixtures":[{"date":"2022-07-16T12:00:00+00:00","home":{"id":260,"name":"OH Leuven","logo":"https:\/\/media.api-sports.io\/football\/teams\/260.png"},"away":{"id":46,"name":"Leicester","logo":"https:\/\/media.api-sports.io\/football\/teams\/46.png"}},{"date":"2022-07-23T14:00:00+00:00","home":{"id":59,"name":"Preston","logo":"https:\/\/media.api-sports.io\/football\/teams\/59.png"},"away":{"id":46,"name":"Leicester","logo":"https:\/\/media.api-sports.io\/football\/teams\/46.png"}},{"date":"2022-08-07T13:00:00+00:00","home":{"id":46,"name":"Leicester","logo":"https:\/\/media.api-sports.io\/football\/teams\/46.png"},"away":{"id":55,"name":"Brentford","logo":"https:\/\/media.api-sports.io\/football\/teams\/55.png"}},{"date":"2022-08-13T14:00:00+00:00","home":{"id":42,"name":"Arsenal","logo":"https:\/\/media.api-sports.io\/football\/teams\/42.png"},"away":{"id":46,"name":"Leicester","logo":"https:\/\/media.api-sports.io\/football\/teams\/46.png"}},{"date":"2022-08-20T14:00:00+00:00","home":{"id":46,"name":"Leicester","logo":"https:\/\/media.api-sports.io\/football\/teams\/46.png"},"away":{"id":41,"name":"Southampton","logo":"https:\/\/media.api-sports.io\/football\/teams\/41.png"}}]}