{"fixtures":[{"date":"2022-10-25T19:00:00+00:00","home":{"id":211,"name":"Benfica","logo":"https://media.api-sports.io/football/teams/211.png"},"away":{"id":496,"name":"Juventus","logo":"https://media.api-sports.io/football/teams/496.png"}},{"date":"2022-10-29T16:00:00+00:00","home":{"id":867,"name":"Lecce","logo":"https://media.api-sports.io/football/teams/867.png"},"away":{"id":496,"name":"Juventus","logo":"https://media.api-sports.io/football/teams/496.png"}},{"date":"2022-11-02T20:00:00+00:00","home":{"id":496,"name":"Juventus","logo":"https://media.api-sports.io/football/teams/496.png"},"away":{"id":85,"name":"Paris Saint Germain","logo":"https://media.api-sports.io/football/teams/85.png"}},{"date":"2022-11-06T19:45:00+00:00","home":{"id":496,"name":"Juventus","logo":"https://media.api-sports.io/football/teams/496.png"},"away":{"id":505,"name":"Inter","logo":"https://media.api-sports.io/football/teams/505.png"}},{"date":"2022-11-10T17:30:00+00:00","home":{"id":504,"name":"Verona","logo":"https://media.api-sports.io/football/teams/504.png"},"away":{"id":496,"name":"Juventus","logo":"https://media.api-sports.io/football/teams/496.png"}}]}