{"fixtures":[{"date":"2022-10-23T16:30:00+00:00","home":{"id":533,"name":"Villarreal","logo":"https://media.api-sports.io/football/teams/533.png"},"away":{"id":723,"name":"Almeria","logo":"https://media.api-sports.io/football/teams/723.png"}},{"date":"2022-10-27T16:45:00+00:00","home":{"id":533,"name":"Villarreal","logo":"https://media.api-sports.io/football/teams/533.png"},"away":{"id":563,"name":"Hapoel Beer Sheva","logo":"https://media.api-sports.io/football/teams/563.png"}},{"date":"2022-10-30T17:30:00+00:00","home":{"id":531,"name":"Athletic Club","logo":"https://media.api-sports.io/football/teams/531.png"},"away":{"id":533,"name":"Villarreal","logo":"https://media.api-sports.io/football/teams/533.png"}},{"date":"2022-11-03T20:00:00+00:00","home":{"id":347,"name":"Lech Poznan","logo":"https://media.api-sports.io/football/teams/347.png"},"away":{"id":533,"name":"Villarreal","logo":"https://media.api-sports.io/football/teams/533.png"}},{"date":"2022-11-06T17:30:00+00:00","home":{"id":533,"name":"Villarreal","logo":"https://media.api-sports.io/football/teams/533.png"},"away":{"id":798,"name":"Mallorca","logo":"https://media.api-sports.io/football/teams/798.png"}}]}